pilton.py
pilton-1.1.1.dist-info/METADATA
pilton-1.1.1.dist-info/WHEEL
pilton-1.1.1.dist-info/top_level.txt
pilton-1.1.1.dist-info/RECORD
