Metadata-Version: 2.1
Name: pilton
Version: 1.1.1
Summary: UNKNOWN
Home-page: UNKNOWN
License: Creative Commons Attribution-Noncommercial-Share Alike license
Platform: UNKNOWN
Requires-Dist: python-shell-colors
